rbm3/__init__.py
rbm3/core/__init__.py
rbm3/core/dice.py
rbm3/core/eval.py
rbm3/core/paras.py
rbm3/core/utils.py
rbm3/scripts/__init__.py
rbm3/scripts/rat_brain-3d_unet.hdf5
rbm3/scripts/rbm3.py
rbm3-0.0.5.dist-info/METADATA
rbm3-0.0.5.dist-info/WHEEL
rbm3-0.0.5.dist-info/entry_points.txt
rbm3-0.0.5.dist-info/top_level.txt
rbm3-0.0.5.dist-info/RECORD
