Metadata-Version: 2.1
Name: rbm3
Version: 0.0.5
Summary: Rodent Brain Masking Tool with Keras 3D Unet
Home-page: UNKNOWN
Author: Not specified yet
Author-email: 
Maintainer: SungHo Lee
Maintainer-email: shlee@unc.edu
License: GNLv3
Keywords: rodent brain masking
Platform: UNKNOWN
Classifier: Development Status :: 5 - Production/Stable
Classifier: Intended Audience :: Science/Research
Classifier: Topic :: Scientific/Engineering :: Medical Science Apps.
Classifier: Natural Language :: English
Classifier: Programming Language :: Python :: 3.7
Requires-Python: >3.5, <3.8
Requires-Dist: keras (>=2.3.0)
Requires-Dist: SimpleITK (>=1.2.4)
Requires-Dist: numpy (>=1.18.0)
Requires-Dist: tensorflow (>=2.0.0)
